README.md
setup.py
pogui/__init__.py
pogui/pogui.py
pogui.egg-info/PKG-INFO
pogui.egg-info/SOURCES.txt
pogui.egg-info/dependency_links.txt
pogui.egg-info/entry_points.txt
pogui.egg-info/requires.txt
pogui.egg-info/top_level.txt
pogui/config/__init__.py
pogui/config/config.py
pogui/lib/__init__.py
pogui/lib/async_ops.py
pogui/lib/path_tools.py
pogui/web/api.js
pogui/web/base.js
pogui/web/create-archive.js
pogui/web/index.html
pogui/web/jquery-3.4.1.js
pogui/web/main.css
pogui/web/navigation.js
pogui/web/settings.js
pogui/web/checklist/cl.js
pogui/web/css.gg/icons.css
pogui/web/filebrowser/fb-state.js
pogui/web/filebrowser/fb.css
pogui/web/filebrowser/fb.js
pogui/web/hover-zoom/hover-zoom.css
pogui/web/hover-zoom/hz.js
pogui/web/loading/progress-bar.css
pogui/web/loading/progress-bar.js
pogui/web/loading/ripple.css
pogui/web/pure/pure.css
pogui/web/pure-layout-side-menu/side-menu.css
pogui/web/pure-layout-side-menu/ui.js