Metadata-Version: 2.1
Name: pogui
Version: 0.0.4
Summary: File encryption and backup GUI
Home-page: https://github.com/sz3/pogui
Author: Stephen Zimmerman
Author-email: sz@galacticicecube.com
License: MIT
Platform: UNKNOWN
Classifier: License :: OSI Approved :: MIT License
Classifier: Programming Language :: JavaScript
Classifier: Programming Language :: Python :: 3
Classifier: Programming Language :: Python :: 3.6
Classifier: Programming Language :: Python :: 3.7
Classifier: Programming Language :: Python :: 3.8
Requires-Python: >=3.6
Provides-Extra: qt
